appmetrica/__init__.py
appmetrica/base.py
appmetrica/exceptions.py
appmetrica/utils.py
appmetrica/export/__init__.py
appmetrica/export/api.py
appmetrica/export/exceptions.py
appmetrica/push/__init__.py
appmetrica/push/api.py
appmetrica/push/exceptions.py
appmetrica/stat/__init__.py
appmetrica/stat/api.py
appmetrica-1.0.7.dist-info/LICENSE
appmetrica-1.0.7.dist-info/METADATA
appmetrica-1.0.7.dist-info/WHEEL
appmetrica-1.0.7.dist-info/top_level.txt
appmetrica-1.0.7.dist-info/RECORD
