Metadata-Version: 2.1
Name: appmetrica
Version: 1.0.7
Summary: API for integration with Yandex AppMetrica
Home-page: https://github.com/MyBook/appmetrica
Author: MyBook
Author-email: dev@mybook.ru
License: BSD
Keywords: appmetrica
Platform: UNKNOWN
Classifier: Development Status :: 5 - Production/Stable
Classifier: Intended Audience :: Developers
Classifier: License :: OSI Approved :: BSD License
Classifier: Natural Language :: English
Classifier: Programming Language :: Python :: 2
Classifier: Programming Language :: Python :: 2.7
Classifier: Programming Language :: Python :: 3
Classifier: Programming Language :: Python :: 3.5
Classifier: Programming Language :: Python :: 3.6
Classifier: Programming Language :: Python :: 3.7
Classifier: Programming Language :: Python :: 3.8
Requires-Dist: requests (>=2.10.0)
